__init__.py
retriever_transformers/models/CrossAttentionDistancePredictor.py
retriever_transformers/models/DualBertEncoder.py
retriever_transformers/models/FeedForwardDistancePredictor.py
retriever_transformers/models/SingleBertEmbedder.py
retriever_transformers/models/__init__.py
retriever_transformers/retrievers/BertEmbedderRetriever.py
retriever_transformers/retrievers/CrossAttentionRetriever.py
retriever_transformers/retrievers/__init__.py
retriever_transformers/retrievers/embedder.py
retriever_transformers/retrievers/retriever.py
tests/__init__.py
tests/models/__init__.py
tests/models/test_CrossAttentionDistancePredictor.py
tests/models/test_SingleBertEmbedder.py
tests/retrievers/__init__.py
tests/retrievers/test_BertEmbedderRetriever.py
tests/retrievers/test_CrossAttentionRetriever.py
retriever_transformers-0.1.1.dist-info/METADATA
retriever_transformers-0.1.1.dist-info/WHEEL
retriever_transformers-0.1.1.dist-info/top_level.txt
retriever_transformers-0.1.1.dist-info/RECORD
